llama_index/callbacks/uptrain/__init__.py
llama_index/callbacks/uptrain/base.py
llama_index_callbacks_uptrain-0.5.1.dist-info/METADATA
llama_index_callbacks_uptrain-0.5.1.dist-info/WHEEL
llama_index_callbacks_uptrain-0.5.1.dist-info/licenses/LICENSE
llama_index_callbacks_uptrain-0.5.1.dist-info/RECORD
