Metadata-Version: 2.4
Name: llama-index-callbacks-uptrain
Version: 0.5.1
Summary: UpTrain Callback for performing evaluations on the LlamaIndex pipeline
Author-email: Dhruv Chawla <dhruv@uptrain.ai>
License-Expression: AGPL-3.0
License-File: LICENSE
Requires-Python: <4.0,>=3.9
Requires-Dist: llama-index-core<0.15,>=0.13.0
Requires-Dist: uptrain>=0.7.1
